CONTRIBUTORS.txt
MANIFEST.in
README.rst
requirements.txt
setup.py
tox.ini
django_optionsfield.egg-info/PKG-INFO
django_optionsfield.egg-info/SOURCES.txt
django_optionsfield.egg-info/dependency_links.txt
django_optionsfield.egg-info/requires.txt
django_optionsfield.egg-info/top_level.txt
docs/Makefile
docs/conf.py
docs/index.rst
docs/make.bat
optionsfield/__init__.py
optionsfield/_version.py
optionsfield/codec.py
optionsfield/conf.py
optionsfield/default_settings.py
optionsfield/fields.py
optionsfield/options.py
optionsfield/tests.py
optionsfield/widgets.py
optionsfield/.ropeproject/config.py
optionsfield/.ropeproject/globalnames
optionsfield/.ropeproject/history
optionsfield/.ropeproject/objectdb
optionsfield/templates/admin/optionsfield/widget.html
requirements/base.txt
requirements/dev.txt
requirements/production.txt
requirements/test.txt