Metadata-Version: 1.1
Name: django-optionsfield
Version: 0.1.2
Summary: django-optionsfield
Home-page: http://github.com/revsquare/django-optionsfield
Author: Rafał Selewońko
Author-email: rafal@selewonko.com
License: MIT
Platform: UNKNOWN
Classifier: Operating System :: OS Independent
Classifier: Programming Language :: Python
Classifier: Programming Language :: Python :: 3
Classifier: Programming Language :: Python :: 3.2
Classifier: Programming Language :: Python :: 3.3
Classifier: Programming Language :: Python :: 3.4
Classifier: Topic :: Internet :: WWW/HTTP
